Metadata-Version: 1.0
Name: teim-distributions
Version: 0.1
Summary: Gaussian distributions
Home-page: UNKNOWN
Author: Nick Teim
Author-email: UNKNOWN
License: UNKNOWN
Platform: UNKNOWN
